parameter/__init__.py
parameter/dh.py
parameter/dt.py
parameter/gauss_class.py
parameter/roughness.py
parameter/util.py
parameter/vh.py
parameter/vt.py
tests/__init__.py
tests/test_dh.py
tests/test_dt.py
tests/test_gauss_class.py
tests/test_roughness.py
tests/test_util.py
tests/test_vh.py
tests/test_vt.py
avant-0.0.1.dist-info/LICENSE
avant-0.0.1.dist-info/METADATA
avant-0.0.1.dist-info/WHEEL
avant-0.0.1.dist-info/top_level.txt
avant-0.0.1.dist-info/RECORD
