Metadata-Version: 2.1
Name: avant
Version: 0.0.1
Summary: A Python package to create informed prior probability distributions for reflectometry analysis
Home-page: https://github.com/nf679/avant
Author: Nicola Farmer
Author-email: nkf679@gmail.com
License: UNKNOWN
Project-URL: docs, https://avant.readthedocs.io/en/latest/
Platform: UNKNOWN
Classifier: Programming Language :: Python :: 3
Classifier: License :: OSI Approved :: MIT License
Classifier: Operating System :: OS Independent
Requires-Python: >=3.6
License-File: LICENSE
